taskiq_redis/__init__.py
taskiq_redis/exceptions.py
taskiq_redis/list_schedule_source.py
taskiq_redis/py.typed
taskiq_redis/redis_backend.py
taskiq_redis/redis_broker.py
taskiq_redis/redis_cluster_broker.py
taskiq_redis/redis_sentinel_broker.py
taskiq_redis/schedule_source.py
taskiq_redis-1.2.1.dist-info/licenses/LICENSE
taskiq_redis-1.2.1.dist-info/WHEEL
taskiq_redis-1.2.1.dist-info/METADATA
taskiq_redis-1.2.1.dist-info/RECORD
