Metadata-Version: 2.4
Name: taskiq-redis
Version: 1.2.1
Summary: Redis integration for taskiq
Keywords: async,distributed,redis,result_backend,taskiq,tasks
Author: Taskiq team
Author-email: Taskiq team <taskiq@no-reply.com>
License-Expression: MIT
License-File: LICENSE
Classifier: Programming Language :: Python
Classifier: Programming Language :: Python :: 3
Classifier: Programming Language :: Python :: 3 :: Only
Classifier: Programming Language :: Python :: 3.10
Classifier: Programming Language :: Python :: 3.11
Classifier: Programming Language :: Python :: 3.12
Classifier: Programming Language :: Python :: 3.13
Requires-Dist: redis>=7.0.0,<8
Requires-Dist: taskiq>=0.12.0
Maintainer: Taskiq team
Maintainer-email: Taskiq team <taskiq@no-reply.com>
Requires-Python: >=3.10
Project-URL: homepage, https://github.com/taskiq-python/taskiq-redis
Project-URL: repository, https://github.com/taskiq-python/taskiq-redis
